{
  "updated_at": "2026-07-16T16:34:00.855757+00:00",
  "symbol": "EUR/USD",
  "stats": {
    "wins": 0,
    "losses": 1,
    "open": 1,
    "total": 2,
    "win_rate": 0.0
  },
  "weights": {
    "bbands": 1.5,
    "ema_trend": 0.8,
    "ma_cross": 0.8,
    "macd": 1.5,
    "rsi": 2.0,
    "stoch": 2.0,
    "supertrend": 0.8
  },
  "equity": [
    -1
  ],
  "demo": {
    "initial_balance": 100.0,
    "balance": 100.0,
    "pnl_total": 0.0,
    "return_pct": 0.0,
    "risk_pct": 2.0,
    "balance_history": [
      100.0,
      100.0
    ],
    "per_signal_pnl": {
      "39": 0.0
    }
  },
  "mt5_account": {},
  "mt5_trades": [],
  "cycle_status": {
    "checked_at": "2026-07-16T16:34:00.848676+00:00",
    "signal_result": "data_error",
    "reason": "MT5 data fetch failed: MT5: no candle data for EURUSD 1h. Error: (-10001, 'IPC send failed')"
  },
  "laptop_battery": {
    "percent": 78,
    "charging": true,
    "secsleft": null
  },
  "signals": [
    {
      "id": 40,
      "created_at": "2026-07-16T14:37:29.804863+00:00",
      "direction": "BUY",
      "entry": 1.1446,
      "tp": 1.14525,
      "sl": 1.14329,
      "score": 2.0,
      "contributors": {
        "rsi": 0,
        "ma_cross": 0,
        "macd": -1,
        "bbands": 1,
        "ema_trend": 1,
        "stoch": 1,
        "supertrend": -1
      },
      "status": "OPEN",
      "closed_at": null,
      "close_price": null,
      "tp1": 1.14525,
      "tp2": 1.14591,
      "confidence": 57,
      "rr": 0.5,
      "trend_strength": 20,
      "timeframe": "30m",
      "lot_size": 15.26,
      "trade_num": 1,
      "pair_id": null,
      "breakeven_active": false,
      "pnl": null,
      "balance_after": null
    },
    {
      "id": 39,
      "created_at": "2026-07-15T17:22:09.679342+00:00",
      "direction": "SELL",
      "entry": 1.14516,
      "tp": 1.14346,
      "sl": 1.14742,
      "score": -2.8,
      "contributors": {
        "rsi": -1,
        "ma_cross": 0,
        "macd": 1,
        "bbands": -1,
        "ema_trend": 1,
        "stoch": -1,
        "supertrend": 1
      },
      "status": "LOSS",
      "closed_at": "2026-07-15T17:47:36.523162",
      "close_price": 1.14516,
      "tp1": 1.14346,
      "tp2": 1.1412,
      "confidence": 63,
      "rr": 0.75,
      "trend_strength": 24,
      "timeframe": "1h",
      "lot_size": 8.84,
      "trade_num": 1,
      "pair_id": null,
      "breakeven_active": false,
      "pnl": 0.0,
      "balance_after": 100.0
    }
  ]
}